mashov/__init__.py
mashov/client.py
mashov/exceptions.py
mashov/models.py
mashov/session.py
pymashov-0.0.2.dist-info/licenses/LICENSE
pymashov-0.0.2.dist-info/METADATA
pymashov-0.0.2.dist-info/WHEEL
pymashov-0.0.2.dist-info/top_level.txt
pymashov-0.0.2.dist-info/RECORD
